{"metadata": {"dbt_schema_version": "https://schemas.getdbt.com/dbt/run-results/v6.json", "dbt_version": "1.10.2", "generated_at": "2025-06-22T19:56:33.596878Z", "invocation_id": "f0c0e8f3-5066-4e1c-8a40-b14095ce2a72", "invocation_started_at": "2025-06-22T19:56:28.986085Z", "env": {}}, "results": [{"status": "success", "timing": [{"name": "compile", "started_at": "2025-06-22T19:56:33.260338Z", "completed_at": "2025-06-22T19:56:33.267513Z"}, {"name": "execute", "started_at": "2025-06-22T19:56:33.267970Z", "completed_at": "2025-06-22T19:56:33.267986Z"}], "thread_id": "Thread-1 (worker)", "execution_time": 0.008666515350341797, "adapter_response": {}, "message": null, "failures": null, "unique_id": "model.sql_examples.weather_data_model", "compiled": true, "compiled_code": "-- models/weather_data_model.sql\n\nSELECT\n    CITY,\n    TEMP_C,\n    HUMIDITY,\n    WIND_SPEED,\n    DESCRIPTION\nFROM MY_DB.MY_SCHEMA.WEATHER_DATA", "relation_name": "MY_DB.MY_SCHEMA.weather_data_model", "batch_results": null}, {"status": "success", "timing": [{"name": "compile", "started_at": "2025-06-22T19:56:33.270478Z", "completed_at": "2025-06-22T19:56:33.273252Z"}, {"name": "execute", "started_at": "2025-06-22T19:56:33.273691Z", "completed_at": "2025-06-22T19:56:33.273700Z"}], "thread_id": "Thread-1 (worker)", "execution_time": 0.004189491271972656, "adapter_response": {}, "message": null, "failures": null, "unique_id": "model.sql_examples.my_first_dbt_model", "compiled": true, "compiled_code": "/*\n    Welcome to your first dbt model!\n    Did you know that you can also configure models directly within SQL files?\n    This will override configurations stated in dbt_project.yml\n\n    Try changing \"table\" to \"view\" below\n*/\n\n\n\nselect\n    CITY,\n    TEMP_C,\n    HUMIDITY,\n    WIND_SPEED,\n    DESCRIPTION\nfrom MY_DB.MY_SCHEMA.weather_data_model\nwhere TEMP_C is not null\n\n/*\n    Uncomment the line below to remove records with null `id` values\n*/\n\n-- where id is not null", "relation_name": "MY_DB.MY_SCHEMA.my_first_dbt_model", "batch_results": null}, {"status": "success", "timing": [{"name": "compile", "started_at": "2025-06-22T19:56:33.275893Z", "completed_at": "2025-06-22T19:56:33.287797Z"}, {"name": "execute", "started_at": "2025-06-22T19:56:33.288282Z", "completed_at": "2025-06-22T19:56:33.288292Z"}], "thread_id": "Thread-1 (worker)", "execution_time": 0.013457059860229492, "adapter_response": {}, "message": null, "failures": null, "unique_id": "test.sql_examples.not_null_weather_data_model_CITY.8a3eedf244", "compiled": true, "compiled_code": "\n    \n    \n\n\n\nselect CITY\nfrom MY_DB.MY_SCHEMA.weather_data_model\nwhere CITY is null\n\n\n", "relation_name": null, "batch_results": null}, {"status": "success", "timing": [{"name": "compile", "started_at": "2025-06-22T19:56:33.290465Z", "completed_at": "2025-06-22T19:56:33.294361Z"}, {"name": "execute", "started_at": "2025-06-22T19:56:33.294805Z", "completed_at": "2025-06-22T19:56:33.294815Z"}], "thread_id": "Thread-1 (worker)", "execution_time": 0.005394458770751953, "adapter_response": {}, "message": null, "failures": null, "unique_id": "test.sql_examples.not_null_weather_data_model_TEMP_C.36028dbf6b", "compiled": true, "compiled_code": "\n    \n    \n\n\n\nselect TEMP_C\nfrom MY_DB.MY_SCHEMA.weather_data_model\nwhere TEMP_C is null\n\n\n", "relation_name": null, "batch_results": null}, {"status": "success", "timing": [{"name": "compile", "started_at": "2025-06-22T19:56:33.296865Z", "completed_at": "2025-06-22T19:56:33.299312Z"}, {"name": "execute", "started_at": "2025-06-22T19:56:33.299751Z", "completed_at": "2025-06-22T19:56:33.299759Z"}], "thread_id": "Thread-1 (worker)", "execution_time": 0.0038881301879882812, "adapter_response": {}, "message": null, "failures": null, "unique_id": "model.sql_examples.my_second_dbt_model", "compiled": true, "compiled_code": "-- Use the `ref` function to select from other models\n\nselect *\nfrom MY_DB.MY_SCHEMA.my_first_dbt_model\nwhere id = 1", "relation_name": "MY_DB.MY_SCHEMA.my_second_dbt_model", "batch_results": null}, {"status": "success", "timing": [{"name": "compile", "started_at": "2025-06-22T19:56:33.301834Z", "completed_at": "2025-06-22T19:56:33.305635Z"}, {"name": "execute", "started_at": "2025-06-22T19:56:33.306091Z", "completed_at": "2025-06-22T19:56:33.306100Z"}], "thread_id": "Thread-1 (worker)", "execution_time": 0.005244255065917969, "adapter_response": {}, "message": null, "failures": null, "unique_id": "test.sql_examples.not_null_my_first_dbt_model_city.6a9ce71ece", "compiled": true, "compiled_code": "\n    \n    \n\n\n\nselect city\nfrom MY_DB.MY_SCHEMA.my_first_dbt_model\nwhere city is null\n\n\n", "relation_name": null, "batch_results": null}, {"status": "success", "timing": [{"name": "compile", "started_at": "2025-06-22T19:56:33.308149Z", "completed_at": "2025-06-22T19:56:33.314052Z"}, {"name": "execute", "started_at": "2025-06-22T19:56:33.314505Z", "completed_at": "2025-06-22T19:56:33.314514Z"}], "thread_id": "Thread-1 (worker)", "execution_time": 0.00732421875, "adapter_response": {}, "message": null, "failures": null, "unique_id": "test.sql_examples.unique_my_first_dbt_model_city.37dd3f2c0c", "compiled": true, "compiled_code": "\n    \n    \n\nselect\n    city as unique_field,\n    count(*) as n_records\n\nfrom MY_DB.MY_SCHEMA.my_first_dbt_model\nwhere city is not null\ngroup by city\nhaving count(*) > 1\n\n\n", "relation_name": null, "batch_results": null}], "elapsed_time": 2.7433218955993652, "args": {"log_level": "info", "use_colors_file": true, "state_modified_compare_vars": false, "partial_parse_file_diff": true, "require_all_warnings_handled_by_warn_error": false, "send_anonymous_usage_stats": true, "skip_nodes_if_on_run_start_fails": false, "log_format": "default", "require_resource_names_without_spaces": true, "static_parser": true, "log_file_max_bytes": 10485760, "exclude": [], "compile": true, "strict_mode": false, "log_format_file": "debug", "validate_macro_args": false, "populate_cache": true, "show_all_deprecations": false, "warn_error_options": {"error": [], "warn": [], "silence": []}, "state_modified_compare_more_unrendered_values": false, "introspect": true, "project_dir": "/home/runner/work/Portfolio/Portfolio/data_engineer/sql_examples", "require_explicit_package_overrides_for_builtin_materializations": true, "macro_debugging": false, "defer": false, "log_level_file": "debug", "log_path": "/home/runner/work/Portfolio/Portfolio/data_engineer/sql_examples/logs", "empty_catalog": false, "print": true, "require_nested_cumulative_type_params": false, "show_resource_report": false, "use_fast_test_edges": false, "favor_state": false, "version_check": true, "vars": {}, "upload_to_artifacts_ingest_api": false, "printer_width": 80, "which": "generate", "invocation_command": "dbt docs generate", "indirect_selection": "eager", "select": [], "profiles_dir": "/home/runner/.dbt", "require_yaml_configuration_for_mf_time_spines": false, "require_batched_execution_for_custom_microbatch_strategy": false, "source_freshness_run_project_hooks": true, "static": false, "quiet": false, "write_json": true, "use_colors": true, "partial_parse": true, "cache_selected_only": false}}